jupyter_anywidget_pandoc/__init__.py
jupyter_anywidget_pandoc/magics.py
jupyter_anywidget_pandoc/panel.py
jupyter_anywidget_pandoc/static/pandoc.css
jupyter_anywidget_pandoc/static/pandoc.js
jupyter_anywidget_pandoc/static/uuid.js
jupyter_anywidget_pandoc/static/widget.css
jupyter_anywidget_pandoc/static/widget.js
jupyter_anywidget_pandoc-0.0.5.dist-info/METADATA
jupyter_anywidget_pandoc-0.0.5.dist-info/WHEEL
jupyter_anywidget_pandoc-0.0.5.dist-info/licenses/LICENSE
jupyter_anywidget_pandoc-0.0.5.dist-info/RECORD
