Metadata-Version: 2.3
Name: jupyter_anywidget_pandoc
Version: 0.0.5
Summary: Jupyter anywidget for sideloading pandoc wasm
Author-email: Tony Hirst <tony.hirst@gmail.com>
Requires-Dist: anywidget
Provides-Extra: dev
Requires-Dist: jupyterlab; extra == 'dev'
Requires-Dist: watchfiles; extra == 'dev'
